LICENSE
MANIFEST.in
README.md
setup.py
pycutter/__init__.py
pycutter/main.py
pycutter/command/__init__.py
pycutter/command/ci.py
pycutter/command/gitignore.py
pycutter/command/managers.py
pycutter/command/vcs.py
python_cutter.egg-info/PKG-INFO
python_cutter.egg-info/SOURCES.txt
python_cutter.egg-info/dependency_links.txt
python_cutter.egg-info/entry_points.txt
python_cutter.egg-info/not-zip-safe
python_cutter.egg-info/requires.txt
python_cutter.egg-info/top_level.txt