Metadata-Version: 2.1
Name: python-cutter
Version: 0.1
Summary: Cookiecutter CLI to start projects in Python
Home-page: https://github.com/alvesgabriel/pycutter
Author: Gabriel Alves
Author-email: gabriel.alves.monteiro1@gmail.com
License: GNU AFFERO GENERAL PUBLIC LICENSE
Platform: UNKNOWN
Classifier: Development Status :: 2 - Pre-Alpha
Classifier: Environment :: Console
Classifier: Intended Audience :: Developers
Classifier: License :: OSI Approved :: GNU Affero General Public License v3 or later (AGPLv3+)
Classifier: Operating System :: OS Independent
Classifier: Programming Language :: Python
Classifier: Programming Language :: Python :: 3.7
Classifier: Framework :: Pytest
